jupyterblack/__init__.py
jupyterblack/__main__.py
jupyterblack/arguments.py
jupyterblack/parser.py
jupyterblack/util/__init__.py
jupyterblack/util/error_messages.py
jupyterblack/util/files.py
jupyterblack/util/processing.py
jupyterblack/util/targets.py
jupyterblack-0.4.1.dist-info/LICENSE
jupyterblack-0.4.1.dist-info/METADATA
jupyterblack-0.4.1.dist-info/WHEEL
jupyterblack-0.4.1.dist-info/entry_points.txt
jupyterblack-0.4.1.dist-info/top_level.txt
jupyterblack-0.4.1.dist-info/RECORD
