Metadata-Version: 2.1
Name: jupyterblack
Version: 0.4.1
Summary: Format code cells in Jupyter Notebook and JupyterLab using black.
Home-page: https://github.com/irahorecka/jupyterblack
Author: Ira Horecka
Author-email: ira89@icloud.com
License: MIT
Platform: UNKNOWN
Classifier: Development Status :: 3 - Alpha
Classifier: License :: OSI Approved :: MIT License
Classifier: Programming Language :: Python
Classifier: Programming Language :: Python :: 3.7
Classifier: Programming Language :: Python :: 3.8
Classifier: Programming Language :: Python :: 3.9
Classifier: Programming Language :: Python :: 3.10
Classifier: Programming Language :: Python :: 3.11
Classifier: Topic :: Software Development :: Libraries
Classifier: Topic :: Software Development :: Libraries :: Python Modules
Classifier: Intended Audience :: Developers
Requires-Python: >=3.7
License-File: LICENSE
Requires-Dist: attrs
Requires-Dist: black
Requires-Dist: safer
Requires-Dist: typing-extensions
